MANIFEST.in
README.md
requirements.txt
setup.py
mpseudo/__init__.py
mpseudo/mpseudo.py
mpseudo/test.py
mpseudo.egg-info/PKG-INFO
mpseudo.egg-info/SOURCES.txt
mpseudo.egg-info/dependency_links.txt
mpseudo.egg-info/requires.txt
mpseudo.egg-info/top_level.txt