Metadata-Version: 1.1
Name: mpseudo
Version: 0.1.3.post1
Summary: Computation of pseudospectra of matrices in parallel
Home-page: https://github.com/scidam/mpseudo
Author: Dmitry E. Kislov
Author-email: kislov@easydan.com
License: UNKNOWN
Keywords: matrix pseudospectra,eigenvalue problem,computational algebra,rectangular matricies
Platform: UNKNOWN
Classifier: Development Status :: 3 - Alpha
Classifier: Intended Audience :: Science/Research
Classifier: License :: OSI Approved :: MIT License
Classifier: Operating System :: OS Independent
Classifier: Programming Language :: Python
Classifier: Programming Language :: Python :: 3
Classifier: Topic :: Scientific/Engineering :: Mathematics
